quoridor/__main__.py
quoridor/client/__main__.py
quoridor/client/sounds/start_sound.wav
quoridor/client/sounds/winning_sound.wav
quoridor/client/src/colors.py
quoridor/client/src/coord.py
quoridor/client/src/network.py
quoridor/client/src/pathfinder.py
quoridor/client/src/player.py
quoridor/client/src/sounds.py
quoridor/client/src/wall.py
quoridor/client/src/widgets.py
quoridor/client/src/window.py
quoridor/server/__main__.py
quoridor/server/src/game.py
quoridor-0.0.3.dist-info/LICENSE
quoridor-0.0.3.dist-info/METADATA
quoridor-0.0.3.dist-info/WHEEL
quoridor-0.0.3.dist-info/top_level.txt
quoridor-0.0.3.dist-info/RECORD
