Metadata-Version: 2.1
Name: quoridor
Version: 0.0.3
Summary: Quoridor Online Game
Home-page: https://github.com/Quentin18/Quoridor-Online
Author: Quentin Deschamps
Author-email: quentindeschamps18@gmail.com
License: UNKNOWN
Platform: UNKNOWN
Classifier: Programming Language :: Python :: 3
Classifier: License :: OSI Approved :: MIT License
Classifier: Operating System :: OS Independent
Requires-Python: >=3.6
Requires-Dist: pathfinding
Requires-Dist: pygame
